{"py/object": "rasa_core.featurizers.MaxHistoryTrackerFeaturizer", "max_history": 5, "remove_duplicates": true, "state_featurizer": {"py/object": "rasa_core.featurizers.BinarySingleStateFeaturizer", "input_state_map": {"entity_location": 12, "entity_name": 13, "entity_user_problem": 14, "intent_ask_location": 0, "intent_ask_name": 1, "intent_ask_problem": 2, "intent_finddoctor": 3, "intent_goodbye": 4, "intent_greet": 5, "intent_introduce": 6, "intent_mood_affirm": 7, "intent_mood_deny": 8, "intent_mood_great": 9, "intent_mood_unhappy": 10, "intent_unknown": 11, "prev_action_default_fallback": 21, "prev_action_listen": 19, "prev_action_restart": 20, "prev_ask_location": 30, "prev_ask_name": 32, "prev_ask_problem": 31, "prev_cheer_up": 23, "prev_did_that_help": 24, "prev_finddoctor": 29, "prev_goodbye": 26, "prev_greet": 22, "prev_happy": 25, "prev_unknown": 27, "prev_welcome": 28, "slot_ask_name_0": 15, "slot_location_0": 16, "slot_name_0": 17, "slot_user_problem_0": 18}, "num_features": 33, "slot_feature_len": 4, "user_feature_len": 15}, "use_intent_probabilities": false}